COPYING.txt
MANIFEST.in
Nikon-SB.png
README.txt
SLR-Camera.png
ebstat.py
setup.py
JBidwatcher_Companion.egg-info/PKG-INFO
JBidwatcher_Companion.egg-info/SOURCES.txt
JBidwatcher_Companion.egg-info/dependency_links.txt
JBidwatcher_Companion.egg-info/requires.txt
JBidwatcher_Companion.egg-info/top_level.txt