Metadata-Version: 1.0
Name: JBidwatcher-Companion
Version: 0.1.7
Summary: Price Statistics for Ebay - Use with JBidwatcher
Home-page: https://launchpad.net/jbidwatcher-companion
Author: Eike Welk
Author-email: Eike.Welk@gmx.net
License: GPL
Platform: UNKNOWN
Classifier: Programming Language :: Python :: 2
Classifier: Development Status :: 4 - Beta
Classifier: Environment :: Console
Classifier: Intended Audience :: End Users/Desktop
Classifier: License :: OSI Approved :: GNU General Public License (GPL)
Classifier: Operating System :: OS Independent
Classifier: Topic :: Office/Business
